<?xml version="1.0" encoding="ISO-8859-1"?>
<facelet-taglib xmlns="http://java.sun.com/xml/ns/javaee"
                xmlns:xsi="http://www.w3.org/2001/XMLSchema-instance"
                xsi:schemaLocation="http://java.sun.com/xml/ns/javaee http://java.sun.com/xml/ns/javaee/web-facelettaglibrary_2_0.xsd"
                version="2.0">
    <namespace>http://gw-systems.com/taglib/thetree</namespace>
    <function>
        <function-name>formatBytes</function-name>
        <function-class>hu.paalgyula.thetree.tags.ByteConveter</function-class>
        <function-signature>java.lang.String formatBytes(java.lang.Long)</function-signature>
    </function>

    <function>
        <function-name>slugify</function-name>
        <function-class>com.github.slugify.Functions</function-class>
        <function-signature>java.lang.String slugify(java.lang.String)</function-signature>
    </function>
</facelet-taglib>
